var_irf/__init__.py
var_irf/core.py
var_irf/plot.py
var_irf-0.1.0.dist-info/licenses/LICENSE
var_irf-0.1.0.dist-info/METADATA
var_irf-0.1.0.dist-info/WHEEL
var_irf-0.1.0.dist-info/top_level.txt
var_irf-0.1.0.dist-info/RECORD
