Metadata-Version: 2.4
Name: var-irf
Version: 0.1.0
Summary: Impulse Response Function (IRF) computation and plotting utilities built on statsmodels VAR
Author: VAR-IRF Maintainers
License: MIT License
Project-URL: Homepage, https://github.com/TianzhuQin/Vector-Autoregression-Impulse-Response-Function
Project-URL: Repository, https://github.com/TianzhuQin/Vector-Autoregression-Impulse-Response-Function.git
Keywords: irf,var,econometrics,time-series,statsmodels,impulse-response
Requires-Python: >=3.9
License-File: LICENSE
Requires-Dist: numpy>=1.21
Requires-Dist: pandas>=1.3
Requires-Dist: statsmodels>=0.13
Requires-Dist: scipy>=1.7
Requires-Dist: matplotlib>=3.5
Dynamic: license-file
